{
  "symbol": "BAJAJFINSV",
  "sector": "Financial Services Financial Services Finance Holding Company",
  "top_ratios": {
    "market_cap": 327841.0,
    "current_price": 2052.0,
    "high": 2195.0,
    "low": 1552.0,
    "pe_ratio": 229.0,
    "book_value": 62.6,
    "dividend_yield": 0.05,
    "roce": 27.4,
    "roe": 20.9,
    "face_value": 1.0
  },
  "quarters": {
    "q_op": {
      "Sep 2022": 625.0,
      "Dec 2022": -10.0,
      "Mar 2023": -6.0,
      "Jun 2023": 541.0,
      "Sep 2023": 959.0,
      "Dec 2023": 0.0,
      "Mar 2024": 5.0,
      "Jun 2024": 850.0,
      "Sep 2024": 1157.0,
      "Dec 2024": 6.0,
      "Mar 2025": 4.0,
      "Jun 2025": 371.0,
      "Sep 2025": 1396.0
    },
    "q_opm": {
      "Sep 2022": 0.93,
      "Dec 2022": -0.31,
      "Mar 2023": -0.19,
      "Jun 2023": 0.91,
      "Sep 2023": 0.95,
      "Dec 2023": 0.01,
      "Mar 2024": 0.1,
      "Jun 2024": 0.93,
      "Sep 2024": 0.95,
      "Dec 2024": 0.08,
      "Mar 2025": 0.06,
      "Jun 2025": 0.85,
      "Sep 2025": 0.95
    },
    "q_interest": {
      "Sep 2022": 0.0,
      "Dec 2022": 0.0,
      "Mar 2023": 0.0,
      "Jun 2023": 0.0,
      "Sep 2023": 0.0,
      "Dec 2023": 0.0,
      "Mar 2024": 0.0,
      "Jun 2024": 0.0,
      "Sep 2024": 0.0,
      "Dec 2024": 0.0,
      "Mar 2025": 0.0,
      "Jun 2025": 0.0,
      "Sep 2025": 0.0
    },
    "q_depreciation": {
      "Sep 2022": 1.0,
      "Dec 2022": 1.0,
      "Mar 2023": 1.0,
      "Jun 2023": 1.0,
      "Sep 2023": 1.0,
      "Dec 2023": 1.0,
      "Mar 2024": 1.0,
      "Jun 2024": 1.0,
      "Sep 2024": 1.0,
      "Dec 2024": 1.0,
      "Mar 2025": 2.0,
      "Jun 2025": 1.0,
      "Sep 2025": 1.0
    },
    "q_pbt": {
      "Sep 2022": 643.0,
      "Dec 2022": 6.0,
      "Mar 2023": 14.0,
      "Jun 2023": 549.0,
      "Sep 2023": 967.0,
      "Dec 2023": 7.0,
      "Mar 2024": 14.0,
      "Jun 2024": 857.0,
      "Sep 2024": 1166.0,
      "Dec 2024": 15.0,
      "Mar 2025": 12.0,
      "Jun 2025": 389.0,
      "Sep 2025": 1403.0
    },
    "q_tax": {
      "Sep 2022": 0.24,
      "Dec 2022": 0.2,
      "Mar 2023": 0.31,
      "Jun 2023": 0.26,
      "Sep 2023": 0.22,
      "Dec 2023": 0.4,
      "Mar 2024": 0.45,
      "Jun 2024": 0.26,
      "Sep 2024": 0.22,
      "Dec 2024": 0.27,
      "Mar 2025": 0.35,
      "Jun 2025": 0.15,
      "Sep 2025": 0.23
    },
    "q_eps": {
      "Sep 2022": 3.05,
      "Dec 2022": 0.03,
      "Mar 2023": 0.06,
      "Jun 2023": 2.53,
      "Sep 2023": 4.73,
      "Dec 2023": 0.03,
      "Mar 2024": 0.05,
      "Jun 2024": 3.96,
      "Sep 2024": 5.68,
      "Dec 2024": 0.07,
      "Mar 2025": 0.05,
      "Jun 2025": 2.06,
      "Sep 2025": 6.79
    }
  },
  "profit_loss": {
    "pl_op": {
      "Mar 2014": 105.0,
      "Mar 2015": 158.0,
      "Mar 2016": 194.0,
      "Mar 2017": 103.0,
      "Mar 2018": 168.0,
      "Mar 2019": 327.0,
      "Mar 2020": 685.0,
      "Mar 2021": 250.0,
      "Mar 2022": 535.0,
      "Mar 2023": 978.0,
      "Mar 2024": 1540.0,
      "Mar 2025": 2054.0,
      "TTM": 1776.0
    },
    "pl_opm": {
      "Mar 2014": 0.68,
      "Mar 2015": 0.76,
      "Mar 2016": 0.78,
      "Mar 2017": 0.63,
      "Mar 2018": 0.67,
      "Mar 2019": 0.73,
      "Mar 2020": 0.84,
      "Mar 2021": 0.64,
      "Mar 2022": 0.77,
      "Mar 2023": 0.85,
      "Mar 2024": 0.89,
      "Mar 2025": 0.89,
      "TTM": 0.87
    },
    "pl_interest": {
      "Mar 2014": 1.0,
      "Mar 2015": 0.0,
      "Mar 2016": 0.0,
      "Mar 2017": 0.0,
      "Mar 2018": 0.0,
      "Mar 2019": 0.0,
      "Mar 2020": 0.0,
      "Mar 2021": 0.0,
      "Mar 2022": 0.0,
      "Mar 2023": 0.0,
      "Mar 2024": 0.0,
      "Mar 2025": 0.0,
      "TTM": 0.0
    },
    "pl_depr": {
      "Mar 2014": 1.0,
      "Mar 2015": 3.0,
      "Mar 2016": 1.0,
      "Mar 2017": 1.0,
      "Mar 2018": 1.0,
      "Mar 2019": 2.0,
      "Mar 2020": 3.0,
      "Mar 2021": 5.0,
      "Mar 2022": 4.0,
      "Mar 2023": 3.0,
      "Mar 2024": 3.0,
      "Mar 2025": 4.0,
      "TTM": 5.0
    },
    "pl_pbt": {
      "Mar 2014": 106.0,
      "Mar 2015": 158.0,
      "Mar 2016": 195.0,
      "Mar 2017": 104.0,
      "Mar 2018": 167.0,
      "Mar 2019": 326.0,
      "Mar 2020": 682.0,
      "Mar 2021": 245.0,
      "Mar 2022": 563.0,
      "Mar 2023": 975.0,
      "Mar 2024": 1537.0,
      "Mar 2025": 2049.0,
      "TTM": 1819.0
    },
    "pl_taxpct": {
      "Mar 2014": 0.21,
      "Mar 2015": 0.2,
      "Mar 2016": 0.16,
      "Mar 2017": 0.33,
      "Mar 2018": 0.15,
      "Mar 2019": 0.06,
      "Mar 2020": 0.02,
      "Mar 2021": 0.27,
      "Mar 2022": 0.25,
      "Mar 2023": 0.25,
      "Mar 2024": 0.24,
      "Mar 2025": 0.24,
      "TTM": null
    },
    "pl_eps": {
      "Mar 2014": 0.52,
      "Mar 2015": 0.79,
      "Mar 2016": 1.03,
      "Mar 2017": 0.44,
      "Mar 2018": 0.89,
      "Mar 2019": 1.93,
      "Mar 2020": 4.19,
      "Mar 2021": 1.12,
      "Mar 2022": 2.67,
      "Mar 2023": 4.6,
      "Mar 2024": 7.33,
      "Mar 2025": 9.76,
      "TTM": 8.97
    },
    "pl_div_payout": {
      "Mar 2014": 0.33,
      "Mar 2015": 0.22,
      "Mar 2016": 0.17,
      "Mar 2017": 0.4,
      "Mar 2018": 0.2,
      "Mar 2019": 0.13,
      "Mar 2020": 0.12,
      "Mar 2021": 0.27,
      "Mar 2022": 0.15,
      "Mar 2023": 0.17,
      "Mar 2024": 0.14,
      "Mar 2025": 0.1,
      "TTM": null
    }
  },
  "balance_sheet": {
    "bs_equity_cap": {
      "Mar 2014": 80.0,
      "Mar 2015": 80.0,
      "Mar 2016": 80.0,
      "Mar 2017": 80.0,
      "Mar 2018": 80.0,
      "Mar 2019": 80.0,
      "Mar 2020": 80.0,
      "Mar 2021": 80.0,
      "Mar 2022": 80.0,
      "Mar 2023": 159.0,
      "Mar 2024": 159.0,
      "Mar 2025": 160.0,
      "Sep 2025": 160.0
    },
    "bs_reserves": {
      "Mar 2014": 2383.0,
      "Mar 2015": 2481.0,
      "Mar 2016": 2616.0,
      "Mar 2017": 2686.0,
      "Mar 2018": 2800.0,
      "Mar 2019": 3055.0,
      "Mar 2020": 3456.0,
      "Mar 2021": 3721.0,
      "Mar 2022": 4289.0,
      "Mar 2023": 5089.0,
      "Mar 2024": 6410.0,
      "Mar 2025": 8212.0,
      "Sep 2025": 9836.0
    },
    "bs_total_liabilities": {
      "Mar 2014": 2537.0,
      "Mar 2015": 2640.0,
      "Mar 2016": 2747.0,
      "Mar 2017": 2814.0,
      "Mar 2018": 2927.0,
      "Mar 2019": 3193.0,
      "Mar 2020": 3600.0,
      "Mar 2021": 3869.0,
      "Mar 2022": 4438.0,
      "Mar 2023": 5318.0,
      "Mar 2024": 6651.0,
      "Mar 2025": 8525.0,
      "Sep 2025": 10223.0
    },
    "bs_cwip": {
      "Mar 2014": 1.0,
      "Mar 2015": 1.0,
      "Mar 2016": 1.0,
      "Mar 2017": 1.0,
      "Mar 2018": 8.0,
      "Mar 2019": 33.0,
      "Mar 2020": 0.0,
      "Mar 2021": 2.0,
      "Mar 2022": 4.0,
      "Mar 2023": 4.0,
      "Mar 2024": 4.0,
      "Mar 2025": 5.0,
      "Sep 2025": 6.0
    },
    "bs_investments": {
      "Mar 2014": 2427.0,
      "Mar 2015": 2514.0,
      "Mar 2016": 2379.0,
      "Mar 2017": 2666.0,
      "Mar 2018": 2758.0,
      "Mar 2019": 2937.0,
      "Mar 2020": 3340.0,
      "Mar 2021": 3495.0,
      "Mar 2022": 4191.0,
      "Mar 2023": 5078.0,
      "Mar 2024": 6401.0,
      "Mar 2025": 7884.0,
      "Sep 2025": 9558.0
    },
    "bs_total_assets": {
      "Mar 2014": 2537.0,
      "Mar 2015": 2640.0,
      "Mar 2016": 2747.0,
      "Mar 2017": 2814.0,
      "Mar 2018": 2927.0,
      "Mar 2019": 3193.0,
      "Mar 2020": 3600.0,
      "Mar 2021": 3869.0,
      "Mar 2022": 4438.0,
      "Mar 2023": 5318.0,
      "Mar 2024": 6651.0,
      "Mar 2025": 8525.0,
      "Sep 2025": 10223.0
    }
  },
  "cash_flow": {
    "cf_net": {
      "Mar 2014": 5.0,
      "Mar 2015": -4.0,
      "Mar 2016": 221.0,
      "Mar 2017": -223.0,
      "Mar 2018": 11.0,
      "Mar 2019": 48.0,
      "Mar 2020": -56.0,
      "Mar 2021": 20.0,
      "Mar 2022": -3.0,
      "Mar 2023": -14.0,
      "Mar 2024": 14.0,
      "Mar 2025": -3.0
    }
  },
  "ratios": {
    "debtor_days": {
      "Mar 2014": 2.0,
      "Mar 2015": 7.0,
      "Mar 2016": 12.0,
      "Mar 2017": 1.0,
      "Mar 2018": 6.0,
      "Mar 2019": 0.0,
      "Mar 2020": 0.0,
      "Mar 2021": 0.0,
      "Mar 2022": 1.0,
      "Mar 2023": 0.0,
      "Mar 2024": 0.0,
      "Mar 2025": 0.0
    },
    "inventory_days": {
      "Mar 2014": null,
      "Mar 2015": null,
      "Mar 2016": null,
      "Mar 2017": null,
      "Mar 2018": null,
      "Mar 2019": null,
      "Mar 2020": null,
      "Mar 2021": null,
      "Mar 2022": null,
      "Mar 2023": null,
      "Mar 2024": null,
      "Mar 2025": null
    },
    "days_payable": {
      "Mar 2014": null,
      "Mar 2015": null,
      "Mar 2016": null,
      "Mar 2017": null,
      "Mar 2018": null,
      "Mar 2019": null,
      "Mar 2020": null,
      "Mar 2021": null,
      "Mar 2022": null,
      "Mar 2023": null,
      "Mar 2024": null,
      "Mar 2025": null
    },
    "ccc": {
      "Mar 2014": 2.0,
      "Mar 2015": 7.0,
      "Mar 2016": 12.0,
      "Mar 2017": 1.0,
      "Mar 2018": 6.0,
      "Mar 2019": 0.0,
      "Mar 2020": 0.0,
      "Mar 2021": 0.0,
      "Mar 2022": 1.0,
      "Mar 2023": 0.0,
      "Mar 2024": 0.0,
      "Mar 2025": 0.0
    },
    "wc_days": {
      "Mar 2014": -126.0,
      "Mar 2015": -80.0,
      "Mar 2016": 1.0,
      "Mar 2017": 17.0,
      "Mar 2018": 23.0,
      "Mar 2019": 18.0,
      "Mar 2020": 11.0,
      "Mar 2021": 25.0,
      "Mar 2022": 23.0,
      "Mar 2023": 15.0,
      "Mar 2024": 7.0,
      "Mar 2025": 54.0
    },
    "roce_pct": {
      "Mar 2014": 0.04,
      "Mar 2015": 0.06,
      "Mar 2016": 0.07,
      "Mar 2017": 0.04,
      "Mar 2018": 0.06,
      "Mar 2019": 0.11,
      "Mar 2020": 0.2,
      "Mar 2021": 0.07,
      "Mar 2022": 0.13,
      "Mar 2023": 0.2,
      "Mar 2024": 0.26,
      "Mar 2025": 0.27
    }
  },
  "growth": {
    "sales_cagr_10y": 0.27,
    "sales_cagr_5y": 0.23,
    "sales_cagr_3y": 0.49,
    "sales_cagr_ttm": -0.08,
    "profit_cagr_10y": 0.29,
    "profit_cagr_5y": 0.19,
    "profit_cagr_3y": 0.57,
    "profit_cagr_ttm": -0.08,
    "price_cagr_10y": 0.26,
    "price_cagr_5y": 0.18,
    "price_cagr_3y": 0.08,
    "price_cagr_1y": 0.28,
    "roe_10y": 0.13,
    "roe_5y": 0.16,
    "roe_3y": 0.19,
    "roe_last_year": 0.21
  },
  "shareholding": {
    "quarterly": {},
    "yearly": {}
  }
}