{
  "symbol": "FORCEMOT",
  "company_name": "Force Motors Ltd",
  "sector": "Automobile and Auto Components",
  "industry": "Passenger Cars & Utility Vehicles",
  "broad_sector": "Consumer Discretionary",
  "market_cap": 23540.0,
  "current_price": 17866.0,
  "week_52_high": 22000.0,
  "week_52_low": 6125.0,
  "pe_ratio": 28.8,
  "book_value": 2720.0,
  "dividend_yield": 0.22,
  "roce_pct": 29.3,
  "roe_pct": 20.2,
  "face_value": 10.0,
  "about": "Force Motors Ltd was established in 1958, is the flagship company of the Abhay Firodia group. The company is in the business of manufacturing fully vertically integrated small and light CVs, multi-utility vehicles, and agricultural tractors, which it supplies to various countries in the Middle East, Asia, Latin America, and Africa. It was known as Bajaj Tempo till 2005[1]",
  "pros": [
    "Company has reduced debt.",
    "Company is almost debt free.",
    "Company has delivered good profit growth of 43.6% CAGR over last 5 years"
  ],
  "cons": [
    "Earnings include an other income of Rs.477 Cr."
  ],
  "quarters": {
    "Sales+": {
      "Sep 2022": 1264.0,
      "Dec 2022": 1304.0,
      "Mar 2023": 1490.0,
      "Jun 2023": 1487.0,
      "Sep 2023": 1802.0,
      "Dec 2023": 1692.0,
      "Mar 2024": 2011.0,
      "Jun 2024": 1885.0,
      "Sep 2024": 1941.0,
      "Dec 2024": 1889.0,
      "Mar 2025": 2356.0,
      "Jun 2025": 2297.0,
      "Sep 2025": 2081.0
    },
    "Expenses+": {
      "Sep 2022": 1165.0,
      "Dec 2022": 1239.0,
      "Mar 2023": 1370.0,
      "Jun 2023": 1307.0,
      "Sep 2023": 1577.0,
      "Dec 2023": 1467.0,
      "Mar 2024": 1733.0,
      "Jun 2024": 1636.0,
      "Sep 2024": 1659.0,
      "Dec 2024": 1658.0,
      "Mar 2025": 2027.0,
      "Jun 2025": 1965.0,
      "Sep 2025": 1719.0
    },
    "Operating Profit": {
      "Sep 2022": 99.0,
      "Dec 2022": 65.0,
      "Mar 2023": 121.0,
      "Jun 2023": 180.0,
      "Sep 2023": 225.0,
      "Dec 2023": 224.0,
      "Mar 2024": 279.0,
      "Jun 2024": 249.0,
      "Sep 2024": 282.0,
      "Dec 2024": 232.0,
      "Mar 2025": 329.0,
      "Jun 2025": 332.0,
      "Sep 2025": 363.0
    },
    "OPM %": {
      "Sep 2022": 8.0,
      "Dec 2022": 5.0,
      "Mar 2023": 8.0,
      "Jun 2023": 12.0,
      "Sep 2023": 12.0,
      "Dec 2023": 13.0,
      "Mar 2024": 14.0,
      "Jun 2024": 13.0,
      "Sep 2024": 15.0,
      "Dec 2024": 12.0,
      "Mar 2025": 14.0,
      "Jun 2025": 14.0,
      "Sep 2025": 17.0
    },
    "Other Income+": {
      "Sep 2022": 12.0,
      "Dec 2022": 5.0,
      "Mar 2023": 246.0,
      "Jun 2023": 11.0,
      "Sep 2023": 9.0,
      "Dec 2023": 4.0,
      "Mar 2024": 15.0,
      "Jun 2024": 15.0,
      "Sep 2024": 9.0,
      "Dec 2024": 15.0,
      "Mar 2025": 413.0,
      "Jun 2025": 25.0,
      "Sep 2025": 24.0
    },
    "Interest": {
      "Sep 2022": 20.0,
      "Dec 2022": 17.0,
      "Mar 2023": 18.0,
      "Jun 2023": 18.0,
      "Sep 2023": 16.0,
      "Dec 2023": 14.0,
      "Mar 2024": 14.0,
      "Jun 2024": 9.0,
      "Sep 2024": 5.0,
      "Dec 2024": 4.0,
      "Mar 2025": 7.0,
      "Jun 2025": 0.0,
      "Sep 2025": 0.0
    },
    "Depreciation": {
      "Sep 2022": 61.0,
      "Dec 2022": 60.0,
      "Mar 2023": 63.0,
      "Jun 2023": 63.0,
      "Sep 2023": 67.0,
      "Dec 2023": 68.0,
      "Mar 2024": 68.0,
      "Jun 2024": 69.0,
      "Sep 2024": 69.0,
      "Dec 2024": 71.0,
      "Mar 2025": 72.0,
      "Jun 2025": 70.0,
      "Sep 2025": 71.0
    },
    "Profit before tax": {
      "Sep 2022": 31.0,
      "Dec 2022": -7.0,
      "Mar 2023": 286.0,
      "Jun 2023": 111.0,
      "Sep 2023": 151.0,
      "Dec 2023": 146.0,
      "Mar 2024": 211.0,
      "Jun 2024": 186.0,
      "Sep 2024": 217.0,
      "Dec 2024": 172.0,
      "Mar 2025": 663.0,
      "Jun 2025": 287.0,
      "Sep 2025": 316.0
    },
    "Tax %": {
      "Sep 2022": 35.0,
      "Dec 2022": -36.0,
      "Mar 2023": 48.0,
      "Jun 2023": 35.0,
      "Sep 2023": 35.0,
      "Dec 2023": 35.0,
      "Mar 2024": 35.0,
      "Jun 2024": 36.0,
      "Sep 2024": 35.0,
      "Dec 2024": 36.0,
      "Mar 2025": 35.0,
      "Jun 2025": 35.0,
      "Sep 2025": -11.0
    },
    "Net Profit+": {
      "Sep 2022": 20.0,
      "Dec 2022": -5.0,
      "Mar 2023": 149.0,
      "Jun 2023": 72.0,
      "Sep 2023": 98.0,
      "Dec 2023": 95.0,
      "Mar 2024": 137.0,
      "Jun 2024": 120.0,
      "Sep 2024": 141.0,
      "Dec 2024": 110.0,
      "Mar 2025": 430.0,
      "Jun 2025": 185.0,
      "Sep 2025": 350.0
    },
    "EPS in Rs": {
      "Sep 2022": 15.16,
      "Dec 2022": -3.45,
      "Mar 2023": 113.2,
      "Jun 2023": 54.62,
      "Sep 2023": 74.57,
      "Dec 2023": 71.9,
      "Mar 2024": 103.75,
      "Jun 2024": 90.76,
      "Sep 2024": 106.77,
      "Dec 2024": 83.53,
      "Mar 2025": 326.07,
      "Jun 2025": 140.57,
      "Sep 2025": 265.26
    },
    "Raw PDF": {
      "Sep 2022": "",
      "Dec 2022": "",
      "Mar 2023": "",
      "Jun 2023": "",
      "Sep 2023": "",
      "Dec 2023": "",
      "Mar 2024": "",
      "Jun 2024": "",
      "Sep 2024": "",
      "Dec 2024": "",
      "Mar 2025": "",
      "Jun 2025": "",
      "Sep 2025": ""
    }
  },
  "profit_loss": {
    "Sales+": {
      "Mar 2014": 2022.0,
      "Mar 2015": 2364.0,
      "Mar 2016": 3025.0,
      "Mar 2017": 3069.0,
      "Mar 2018": 3423.0,
      "Mar 2019": 3652.0,
      "Mar 2020": 3080.0,
      "Mar 2021": 1988.0,
      "Mar 2022": 3240.0,
      "Mar 2023": 5029.0,
      "Mar 2024": 6992.0,
      "Mar 2025": 8071.0,
      "TTM": 8624.0
    },
    "Expenses+": {
      "Mar 2014": 1925.0,
      "Mar 2015": 2217.0,
      "Mar 2016": 2751.0,
      "Mar 2017": 2801.0,
      "Mar 2018": 3155.0,
      "Mar 2019": 3374.0,
      "Mar 2020": 2811.0,
      "Mar 2021": 1952.0,
      "Mar 2022": 3173.0,
      "Mar 2023": 4697.0,
      "Mar 2024": 6082.0,
      "Mar 2025": 6973.0,
      "TTM": 7368.0
    },
    "Operating Profit": {
      "Mar 2014": 97.0,
      "Mar 2015": 147.0,
      "Mar 2016": 274.0,
      "Mar 2017": 268.0,
      "Mar 2018": 267.0,
      "Mar 2019": 278.0,
      "Mar 2020": 269.0,
      "Mar 2021": 36.0,
      "Mar 2022": 67.0,
      "Mar 2023": 331.0,
      "Mar 2024": 910.0,
      "Mar 2025": 1098.0,
      "TTM": 1255.0
    },
    "OPM %": {
      "Mar 2014": 5.0,
      "Mar 2015": 6.0,
      "Mar 2016": 9.0,
      "Mar 2017": 9.0,
      "Mar 2018": 8.0,
      "Mar 2019": 8.0,
      "Mar 2020": 9.0,
      "Mar 2021": 2.0,
      "Mar 2022": 2.0,
      "Mar 2023": 7.0,
      "Mar 2024": 13.0,
      "Mar 2025": 14.0,
      "TTM": 15.0
    },
    "Other Income+": {
      "Mar 2014": 60.0,
      "Mar 2015": 66.0,
      "Mar 2016": 71.0,
      "Mar 2017": 86.0,
      "Mar 2018": 69.0,
      "Mar 2019": 82.0,
      "Mar 2020": 3.0,
      "Mar 2021": 2.0,
      "Mar 2022": 52.0,
      "Mar 2023": 268.0,
      "Mar 2024": 37.0,
      "Mar 2025": 445.0,
      "TTM": 477.0
    },
    "Interest": {
      "Mar 2014": 9.0,
      "Mar 2015": 7.0,
      "Mar 2016": 5.0,
      "Mar 2017": 6.0,
      "Mar 2018": 7.0,
      "Mar 2019": 15.0,
      "Mar 2020": 28.0,
      "Mar 2021": 28.0,
      "Mar 2022": 41.0,
      "Mar 2023": 68.0,
      "Mar 2024": 62.0,
      "Mar 2025": 26.0,
      "TTM": 12.0
    },
    "Depreciation": {
      "Mar 2014": 85.0,
      "Mar 2015": 81.0,
      "Mar 2016": 92.0,
      "Mar 2017": 113.0,
      "Mar 2018": 129.0,
      "Mar 2019": 151.0,
      "Mar 2020": 195.0,
      "Mar 2021": 174.0,
      "Mar 2022": 191.0,
      "Mar 2023": 241.0,
      "Mar 2024": 267.0,
      "Mar 2025": 280.0,
      "TTM": 284.0
    },
    "Profit before tax": {
      "Mar 2014": 63.0,
      "Mar 2015": 125.0,
      "Mar 2016": 248.0,
      "Mar 2017": 235.0,
      "Mar 2018": 200.0,
      "Mar 2019": 194.0,
      "Mar 2020": 50.0,
      "Mar 2021": -164.0,
      "Mar 2022": -113.0,
      "Mar 2023": 291.0,
      "Mar 2024": 618.0,
      "Mar 2025": 1237.0,
      "TTM": 1437.0
    },
    "Tax %": {
      "Mar 2014": -24.0,
      "Mar 2015": 19.0,
      "Mar 2016": 28.0,
      "Mar 2017": 23.0,
      "Mar 2018": 27.0,
      "Mar 2019": 24.0,
      "Mar 2020": -17.0,
      "Mar 2021": -32.0,
      "Mar 2022": -34.0,
      "Mar 2023": 48.0,
      "Mar 2024": 35.0,
      "Mar 2025": 35.0,
      "TTM": ""
    },
    "Net Profit+": {
      "Mar 2014": 78.0,
      "Mar 2015": 101.0,
      "Mar 2016": 179.0,
      "Mar 2017": 180.0,
      "Mar 2018": 147.0,
      "Mar 2019": 147.0,
      "Mar 2020": 58.0,
      "Mar 2021": -112.0,
      "Mar 2022": -75.0,
      "Mar 2023": 152.0,
      "Mar 2024": 402.0,
      "Mar 2025": 800.0,
      "TTM": 1074.0
    },
    "EPS in Rs": {
      "Mar 2014": 58.96,
      "Mar 2015": 76.93,
      "Mar 2016": 135.65,
      "Mar 2017": 136.55,
      "Mar 2018": 111.53,
      "Mar 2019": 111.7,
      "Mar 2020": 44.16,
      "Mar 2021": -84.89,
      "Mar 2022": -56.62,
      "Mar 2023": 115.4,
      "Mar 2024": 304.86,
      "Mar 2025": 607.13,
      "TTM": 815.43
    },
    "Dividend Payout %": {
      "Mar 2014": 5.0,
      "Mar 2015": 6.0,
      "Mar 2016": 7.0,
      "Mar 2017": 7.0,
      "Mar 2018": 9.0,
      "Mar 2019": 9.0,
      "Mar 2020": 23.0,
      "Mar 2021": -6.0,
      "Mar 2022": -18.0,
      "Mar 2023": 9.0,
      "Mar 2024": 7.0,
      "Mar 2025": 7.0,
      "TTM": ""
    }
  },
  "balance_sheet": {
    "Equity Capital": {
      "Mar 2014": 13.0,
      "Mar 2015": 13.0,
      "Mar 2016": 13.0,
      "Mar 2017": 13.0,
      "Mar 2018": 13.0,
      "Mar 2019": 13.0,
      "Mar 2020": 13.0,
      "Mar 2021": 13.0,
      "Mar 2022": 13.0,
      "Mar 2023": 13.0,
      "Mar 2024": 13.0,
      "Mar 2025": 13.0,
      "Sep 2025": 13.0
    },
    "Reserves": {
      "Mar 2014": 1213.0,
      "Mar 2015": 1304.0,
      "Mar 2016": 1474.0,
      "Mar 2017": 1652.0,
      "Mar 2018": 1786.0,
      "Mar 2019": 1922.0,
      "Mar 2020": 1963.0,
      "Mar 2021": 1847.0,
      "Mar 2022": 1774.0,
      "Mar 2023": 1919.0,
      "Mar 2024": 2313.0,
      "Mar 2025": 3090.0,
      "Sep 2025": 3571.0
    },
    "Borrowings+": {
      "Mar 2014": 53.0,
      "Mar 2015": 21.0,
      "Mar 2016": 14.0,
      "Mar 2017": 200.0,
      "Mar 2018": 0.0,
      "Mar 2019": 286.0,
      "Mar 2020": 310.0,
      "Mar 2021": 642.0,
      "Mar 2022": 1069.0,
      "Mar 2023": 955.0,
      "Mar 2024": 524.0,
      "Mar 2025": 17.0,
      "Sep 2025": 0.0
    },
    "Other Liabilities+": {
      "Mar 2014": 493.0,
      "Mar 2015": 634.0,
      "Mar 2016": 800.0,
      "Mar 2017": 734.0,
      "Mar 2018": 720.0,
      "Mar 2019": 615.0,
      "Mar 2020": 821.0,
      "Mar 2021": 755.0,
      "Mar 2022": 842.0,
      "Mar 2023": 1182.0,
      "Mar 2024": 1633.0,
      "Mar 2025": 2081.0,
      "Sep 2025": 1833.0
    },
    "Total Liabilities": {
      "Mar 2014": 1772.0,
      "Mar 2015": 1972.0,
      "Mar 2016": 2301.0,
      "Mar 2017": 2600.0,
      "Mar 2018": 2519.0,
      "Mar 2019": 2836.0,
      "Mar 2020": 3107.0,
      "Mar 2021": 3258.0,
      "Mar 2022": 3698.0,
      "Mar 2023": 4069.0,
      "Mar 2024": 4483.0,
      "Mar 2025": 5202.0,
      "Sep 2025": 5418.0
    },
    "Fixed Assets+": {
      "Mar 2014": 643.0,
      "Mar 2015": 638.0,
      "Mar 2016": 786.0,
      "Mar 2017": 911.0,
      "Mar 2018": 948.0,
      "Mar 2019": 1216.0,
      "Mar 2020": 1400.0,
      "Mar 2021": 1224.0,
      "Mar 2022": 2033.0,
      "Mar 2023": 2094.0,
      "Mar 2024": 2031.0,
      "Mar 2025": 1969.0,
      "Sep 2025": 2115.0
    },
    "CWIP": {
      "Mar 2014": 206.0,
      "Mar 2015": 240.0,
      "Mar 2016": 205.0,
      "Mar 2017": 220.0,
      "Mar 2018": 369.0,
      "Mar 2019": 372.0,
      "Mar 2020": 445.0,
      "Mar 2021": 725.0,
      "Mar 2022": 302.0,
      "Mar 2023": 154.0,
      "Mar 2024": 171.0,
      "Mar 2025": 287.0,
      "Sep 2025": 190.0
    },
    "Investments": {
      "Mar 2014": 1.0,
      "Mar 2015": 1.0,
      "Mar 2016": 15.0,
      "Mar 2017": 10.0,
      "Mar 2018": 11.0,
      "Mar 2019": 28.0,
      "Mar 2020": 92.0,
      "Mar 2021": 126.0,
      "Mar 2022": 154.0,
      "Mar 2023": 159.0,
      "Mar 2024": 166.0,
      "Mar 2025": 178.0,
      "Sep 2025": 178.0
    },
    "Other Assets+": {
      "Mar 2014": 922.0,
      "Mar 2015": 1093.0,
      "Mar 2016": 1296.0,
      "Mar 2017": 1459.0,
      "Mar 2018": 1191.0,
      "Mar 2019": 1220.0,
      "Mar 2020": 1169.0,
      "Mar 2021": 1184.0,
      "Mar 2022": 1209.0,
      "Mar 2023": 1662.0,
      "Mar 2024": 2115.0,
      "Mar 2025": 2768.0,
      "Sep 2025": 2934.0
    },
    "Total Assets": {
      "Mar 2014": 1772.0,
      "Mar 2015": 1972.0,
      "Mar 2016": 2301.0,
      "Mar 2017": 2600.0,
      "Mar 2018": 2519.0,
      "Mar 2019": 2836.0,
      "Mar 2020": 3107.0,
      "Mar 2021": 3258.0,
      "Mar 2022": 3698.0,
      "Mar 2023": 4069.0,
      "Mar 2024": 4483.0,
      "Mar 2025": 5202.0,
      "Sep 2025": 5418.0
    }
  },
  "cash_flow": {
    "Cash from Operating Activity+": {
      "Mar 2014": 116.0,
      "Mar 2015": 226.0,
      "Mar 2016": 256.0,
      "Mar 2017": 471.0,
      "Mar 2018": 256.0,
      "Mar 2019": 312.0,
      "Mar 2020": 409.0,
      "Mar 2021": 7.0,
      "Mar 2022": 18.0,
      "Mar 2023": 531.0,
      "Mar 2024": 1011.0,
      "Mar 2025": 971.0
    },
    "Cash from Investing Activity+": {
      "Mar 2014": -100.0,
      "Mar 2015": -96.0,
      "Mar 2016": -210.0,
      "Mar 2017": -621.0,
      "Mar 2018": -81.0,
      "Mar 2019": -606.0,
      "Mar 2020": -327.0,
      "Mar 2021": -333.0,
      "Mar 2022": -356.0,
      "Mar 2023": -256.0,
      "Mar 2024": -198.0,
      "Mar 2025": -351.0
    },
    "Cash from Financing Activity+": {
      "Mar 2014": -30.0,
      "Mar 2015": -45.0,
      "Mar 2016": -37.0,
      "Mar 2017": 180.0,
      "Mar 2018": -223.0,
      "Mar 2019": 256.0,
      "Mar 2020": -20.0,
      "Mar 2021": 293.0,
      "Mar 2022": 375.0,
      "Mar 2023": -207.0,
      "Mar 2024": -509.0,
      "Mar 2025": -562.0
    },
    "Net Cash Flow": {
      "Mar 2014": -14.0,
      "Mar 2015": 85.0,
      "Mar 2016": 9.0,
      "Mar 2017": 30.0,
      "Mar 2018": -47.0,
      "Mar 2019": -37.0,
      "Mar 2020": 62.0,
      "Mar 2021": -32.0,
      "Mar 2022": 37.0,
      "Mar 2023": 68.0,
      "Mar 2024": 304.0,
      "Mar 2025": 58.0
    }
  },
  "ratios": {
    "ratio_debtor_days": 8.0,
    "ratio_inventory_days": 73.0,
    "ratio_days_payable": 48.0,
    "ratio_cash_conversion_cycle": 32.0,
    "ratio_working_capital_days": 16.0,
    "ratio_roce_pct": 29.0
  },
  "growth": {
    "sales_cagr_10y": 13.0,
    "sales_cagr_5y": 21.0,
    "sales_cagr_3y": 36.0,
    "sales_cagr_ttm": 15.0,
    "profit_cagr_10y": 18.0,
    "profit_cagr_5y": 44.0,
    "profit_cagr_3y": 110.0,
    "profit_cagr_ttm": 66.0,
    "price_cagr_10y": 19.0,
    "price_cagr_5y": 72.0,
    "price_cagr_3y": 128.0,
    "price_cagr_1y": 162.0,
    "roe_10y": 8.0,
    "roe_5y": 8.0,
    "roe_3y": 15.0,
    "roe_last_year": 20.0
  },
  "shareholding": {
    "quarterly": {
      "promoters": {
        "Dec 2022": 61.63,
        "Mar 2023": 61.63,
        "Jun 2023": 61.63,
        "Sep 2023": 61.63,
        "Dec 2023": 61.63,
        "Mar 2024": 61.63,
        "Jun 2024": 61.63,
        "Sep 2024": 61.63,
        "Dec 2024": 61.63,
        "Mar 2025": 61.63,
        "Jun 2025": 61.63,
        "Sep 2025": 61.63
      },
      "fii": {
        "Dec 2022": 2.71,
        "Mar 2023": 2.72,
        "Jun 2023": 4.11,
        "Sep 2023": 4.94,
        "Dec 2023": 4.91,
        "Mar 2024": 6.34,
        "Jun 2024": 7.78,
        "Sep 2024": 7.89,
        "Dec 2024": 8.15,
        "Mar 2025": 8.36,
        "Jun 2025": 9.77,
        "Sep 2025": 10.27
      },
      "dii": {
        "Dec 2022": 2.19,
        "Mar 2023": 2.32,
        "Jun 2023": 1.48,
        "Sep 2023": 1.59,
        "Dec 2023": 1.2,
        "Mar 2024": 0.86,
        "Jun 2024": 1.02,
        "Sep 2024": 0.92,
        "Dec 2024": 0.9,
        "Mar 2025": 1.43,
        "Jun 2025": 1.66,
        "Sep 2025": 1.48
      },
      "public": {
        "Dec 2022": 33.47,
        "Mar 2023": 33.33,
        "Jun 2023": 32.77,
        "Sep 2023": 31.86,
        "Dec 2023": 32.27,
        "Mar 2024": 31.16,
        "Jun 2024": 29.57,
        "Sep 2024": 29.56,
        "Dec 2024": 29.3,
        "Mar 2025": 28.58,
        "Jun 2025": 26.94,
        "Sep 2025": 26.63
      }
    },
    "latest": {
      "promoters": 61.63,
      "fii": 2.71,
      "dii": 2.19,
      "public": 33.47
    },
    "pledge": {}
  },
  "peers": [],
  "eps_ttm": 815.43,
  "debt_to_equity": 0.0,
  "sh_promoters_pct": 61.63,
  "sh_fii_pct": 2.71,
  "sh_dii_pct": 2.19,
  "sh_public_pct": 33.47,
  "sh_govt_pct": null,
  "sales_cagr_10y": 13.0,
  "sales_cagr_5y": 21.0,
  "sales_cagr_3y": 36.0,
  "sales_cagr_ttm": 15.0,
  "profit_cagr_10y": 18.0,
  "profit_cagr_5y": 44.0,
  "profit_cagr_3y": 110.0,
  "profit_cagr_ttm": 66.0,
  "price_cagr_10y": 19.0,
  "price_cagr_5y": 72.0,
  "price_cagr_3y": 128.0,
  "price_cagr_1y": 162.0,
  "roe_10y": 8.0,
  "roe_5y": 8.0,
  "roe_3y": 15.0,
  "roe_last_year": 20.0,
  "ratio_debtor_days": 8.0,
  "ratio_inventory_days": 73.0,
  "ratio_days_payable": 48.0,
  "ratio_cash_conversion_cycle": 32.0,
  "ratio_working_capital_days": 16.0,
  "ratio_roce_pct": 29.0,
  "q_sales_latest": 2081.0,
  "q_net_profit_latest": 350.0,
  "q_eps_latest": 265.26,
  "pl_sales_ttm": 8624.0,
  "pl_net_profit_ttm": 1074.0,
  "_extracted_at": "2025-12-02T15:30:05.667355"
}